fakeyou/__init__.py
fakeyou/asynchronous_fakeyou.py
fakeyou/exception.py
fakeyou/fakeyou.py
fakeyou/objects.py
fakeyou/util/__init__.py
fakeyou/util/exceptions.py
fakeyou/util/objects.py
fakeyou/util/service.py
fakeyou-1.3.0.dist-info/LICENSE
fakeyou-1.3.0.dist-info/METADATA
fakeyou-1.3.0.dist-info/WHEEL
fakeyou-1.3.0.dist-info/top_level.txt
fakeyou-1.3.0.dist-info/RECORD
