Metadata-Version: 2.2
Name: fakeyou
Version: 1.3.0
Summary: Enhanced FAKEYOU.COM API Library
Home-page: https://github.com/AbrinPoison/fakeyou.py
Author: Shards-7
Keywords: fakeyou,fakeyou.py,fakeyou api,rappers voice,sing AI,text to speech,text to singing,text to song,lyrics to song,tts
Classifier: Development Status :: 4 - Beta
Classifier: Intended Audience :: Developers
Classifier: License :: OSI Approved :: MIT License
Classifier: Programming Language :: Python :: 3
Classifier: Programming Language :: Python :: 3.4
Classifier: Programming Language :: Python :: 3.5
Classifier: Programming Language :: Python :: 3.6
Classifier: Programming Language :: Python :: 3.7
Classifier: Programming Language :: Python :: 3.8
Classifier: Programming Language :: Python :: 3.9
Classifier: Operating System :: OS Independent
Requires-Python: >=3.4
License-File: LICENSE
Requires-Dist: requests
Requires-Dist: aiohttp
Dynamic: author
Dynamic: classifier
Dynamic: description
Dynamic: description-content-type
Dynamic: home-page
Dynamic: keywords
Dynamic: requires-dist
Dynamic: requires-python
Dynamic: summary
